{
  "$schema": "http://json-schema.org/draft-07/schema#",
  "title": "VA10091",
  "type": "object",
  "required": [],
  "properties": {
    "date": {
      "type": "string",
      "x-va-field": {
        "label": "Date",
        "widget": "text"
      }
    },
    "stationNumber": {
      "type": "string",
      "x-va-field": {
        "label": "Station Number",
        "widget": "text"
      }
    },
    "stationContact": {
      "type": "string",
      "x-va-field": {
        "label": "Station Contact",
        "widget": "text"
      }
    },
    "stationPhone": {
      "type": "string",
      "x-va-field": {
        "label": "Station Phone",
        "widget": "text"
      }
    },
    "stationFax": {
      "type": "string",
      "x-va-field": {
        "label": "Station Fax",
        "widget": "text"
      }
    },
    "stationEmail": {
      "type": "string",
      "x-va-field": {
        "label": "Station Email",
        "widget": "text"
      }
    },
    "payee": {
      "type": "string",
      "x-va-field": {
        "label": "Payee",
        "widget": "text"
      }
    },
    "factsId": {
      "type": "string",
      "x-va-field": {
        "label": "Facts ID",
        "widget": "text"
      }
    },
    "miscellaneousActions": {
      "type": "string",
      "x-va-field": {
        "label": "Miscellaneous Actions",
        "widget": "text"
      }
    },
    "martinsburgFallingwaters": {
      "type": "boolean",
      "x-va-field": {
        "label": "Martinsburg Fallingwaters",
        "widget": "checkbox"
      }
    },
    "dunsNumber": {
      "type": "string",
      "x-va-field": {
        "label": "Duns Number",
        "widget": "text"
      }
    },
    "duns4": {
      "type": "string",
      "x-va-field": {
        "label": "Duns",
        "widget": "text"
      }
    },
    "ssnTin": {
      "type": "string",
      "x-va-field": {
        "label": "SSN Tin",
        "widget": "text"
      }
    },
    "npi": {
      "type": "string",
      "x-va-field": {
        "label": "Npi",
        "widget": "text"
      }
    },
    "createNew": {
      "type": "boolean",
      "x-va-field": {
        "label": "Create New",
        "widget": "checkbox"
      }
    },
    "payeeName": {
      "type": "string",
      "x-va-field": {
        "label": "Payee Name",
        "widget": "text"
      }
    },
    "dba": {
      "type": "string",
      "x-va-field": {
        "label": "Dba",
        "widget": "text"
      }
    },
    "email": {
      "type": "string",
      "x-va-field": {
        "label": "Email",
        "widget": "text"
      }
    },
    "phone": {
      "type": "string",
      "x-va-field": {
        "label": "Phone",
        "widget": "text"
      }
    },
    "currentAddress": {
      "type": "string",
      "x-va-field": {
        "label": "Current Address",
        "widget": "text"
      }
    },
    "previousAddress": {
      "type": "string",
      "x-va-field": {
        "label": "Previous Address",
        "widget": "text"
      }
    },
    "bankName": {
      "type": "string",
      "x-va-field": {
        "label": "Bank Name",
        "widget": "text"
      }
    },
    "bankRoutingNumber": {
      "type": "string",
      "x-va-field": {
        "label": "Bank Routing Number",
        "widget": "text"
      }
    },
    "accountNumber": {
      "type": "string",
      "x-va-field": {
        "label": "Account Number",
        "widget": "text"
      }
    },
    "accountType": {
      "type": "string",
      "x-va-field": {
        "label": "Account Type",
        "widget": "text"
      }
    },
    "nameTitle": {
      "type": "string",
      "x-va-field": {
        "label": "Name Title",
        "widget": "text"
      }
    },
    "fullName": {
      "type": "string",
      "x-va-field": {
        "label": "Full Name",
        "widget": "text"
      }
    },
    "purposeOfForm": {
      "type": "string",
      "x-va-field": {
        "label": "Purpose of Form",
        "widget": "text"
      }
    },
    "establishOrUp": {
      "type": "string",
      "x-va-field": {
        "label": "Establish or Up",
        "widget": "text"
      }
    },
    "requestType": {
      "type": "string",
      "x-va-field": {
        "label": "Request Type",
        "widget": "text"
      }
    },
    "chooseUp": {
      "type": "string",
      "format": "date",
      "x-va-field": {
        "label": "Choose Up",
        "widget": "date"
      }
    },
    "stationNumber2": {
      "type": "string",
      "x-va-field": {
        "label": "Station Number",
        "widget": "text"
      }
    },
    "stationContact2": {
      "type": "string",
      "x-va-field": {
        "label": "Station Contact",
        "widget": "text"
      }
    },
    "stationPhoneNumber": {
      "type": "string",
      "pattern": "^\\d{10}$",
      "x-va-field": {
        "label": "Station Phone Number",
        "widget": "phone"
      }
    },
    "stationFaxNumber": {
      "type": "string",
      "x-va-field": {
        "label": "Station Fax Number",
        "widget": "text"
      }
    },
    "stationEmailAddress": {
      "type": "string",
      "format": "email",
      "x-va-field": {
        "label": "Station Email Address",
        "widget": "email"
      }
    },
    "payeeVendorTypeRequired": {
      "type": "string",
      "x-va-field": {
        "label": "Payee Vendor Type (Required):",
        "widget": "text"
      }
    },
    "miscellaneousActionsIfApplicable": {
      "type": "string",
      "x-va-field": {
        "label": "Miscellaneous Actions (If applicable):",
        "widget": "text"
      }
    },
    "commercialVendorRegisteredInSamGov": {
      "type": "string",
      "x-va-field": {
        "label": "Commercial Vendor registered in Sam.gov:",
        "widget": "text"
      }
    },
    "uniqueEntityIdentifyUei": {
      "type": "string",
      "x-va-field": {
        "label": "Unique Entity Identify (UEI):",
        "widget": "text"
      }
    },
    "eftIndicator": {
      "type": "string",
      "x-va-field": {
        "label": "EFT Indicator:",
        "widget": "text"
      }
    },
    "blankOrIncorrectInformationInThisFieldMayCauseA": {
      "type": "string",
      "x-va-field": {
        "label": "Blank or Incorrect Information in This Field May Cause a",
        "widget": "text"
      }
    },
    "ssnTin2": {
      "type": "string",
      "pattern": "^\\d{3}-?\\d{2}-?\\d{4}$",
      "maxLength": 11,
      "x-va-field": {
        "label": "SSN/Tin:",
        "widget": "ssn"
      }
    },
    "npi2": {
      "type": "string",
      "x-va-field": {
        "label": "Npi",
        "widget": "text"
      }
    },
    "smallBusiness": {
      "type": "string",
      "x-va-field": {
        "label": "Small Business",
        "widget": "text"
      }
    },
    "payeeVendorName": {
      "type": "string",
      "x-va-field": {
        "label": "Payee Vendor Name",
        "widget": "text"
      }
    },
    "doingBusinessAsDba": {
      "type": "string",
      "x-va-field": {
        "label": "Doing Business As (Dba):",
        "widget": "text"
      }
    },
    "payeeVendorEmail": {
      "type": "string",
      "format": "email",
      "x-va-field": {
        "label": "Payee Vendor Email",
        "widget": "email"
      }
    },
    "emailAddressForThePersonListedInBoxes_24And_25": {
      "type": "string",
      "format": "email",
      "x-va-field": {
        "label": "Email Address for the Person Listed in Boxes 24And",
        "widget": "email"
      }
    },
    "payeeVendorPhoneNumber": {
      "type": "string",
      "pattern": "^\\d{10}$",
      "x-va-field": {
        "label": "Payee Vendor Phone Number",
        "widget": "phone"
      }
    },
    "currentAddress2": {
      "type": "string",
      "x-va-field": {
        "label": "Current Address",
        "widget": "address"
      }
    },
    "previousAddressRequiredForAddressChange": {
      "type": "string",
      "x-va-field": {
        "label": "PREVIOUS ADDRESS (Required for address change",
        "widget": "address"
      }
    },
    "requests": {
      "type": "string",
      "x-va-field": {
        "label": "requests)",
        "widget": "text"
      }
    },
    "currentBankName": {
      "type": "string",
      "x-va-field": {
        "label": "Current Bank Name",
        "widget": "text"
      }
    },
    "currentBank_9DigitRoutingNumber": {
      "type": "string",
      "x-va-field": {
        "label": "Current Bank 9Digit Routing Number",
        "widget": "text"
      }
    },
    "currentBankAccountNumber": {
      "type": "string",
      "x-va-field": {
        "label": "Current Bank Account Number",
        "widget": "text"
      }
    },
    "currentAccountType": {
      "type": "string",
      "x-va-field": {
        "label": "Current Account Type",
        "widget": "text"
      }
    },
    "makesItACrimeTo": {
      "type": "string",
      "x-va-field": {
        "label": "Makes It a Crime to",
        "widget": "text"
      }
    },
    "nameAndTitleOfAuthorizedRepresentative": {
      "type": "string",
      "x-va-field": {
        "label": "Name and Title of Authorized Representative",
        "widget": "text"
      }
    },
    "representativeIsDefinedAs": {
      "type": "string",
      "x-va-field": {
        "label": "Representative is Defined As",
        "widget": "text"
      }
    },
    "signatureOfAuthorizedRepresentative": {
      "type": "string",
      "x-va-field": {
        "label": "Signature of Authorized Representative",
        "widget": "signature"
      }
    },
    "statementOnThisFormCanBePunishedByFineOr": {
      "type": "string",
      "x-va-field": {
        "label": "Statement on This Form Can Be Punished by Fine or",
        "widget": "select"
      }
    },
    "newVendorup": {
      "type": "string",
      "format": "date",
      "x-va-field": {
        "label": "New Vendorup",
        "widget": "date"
      }
    },
    "stationNumber3": {
      "type": "string",
      "x-va-field": {
        "label": "Station Number",
        "widget": "text"
      }
    },
    "stationContact3": {
      "type": "string",
      "x-va-field": {
        "label": "Station Contact",
        "widget": "text"
      }
    },
    "stationPhoneNumber2": {
      "type": "string",
      "pattern": "^\\d{10}$",
      "x-va-field": {
        "label": "Station Phone Number",
        "widget": "phone"
      }
    },
    "stationFaxNumber2": {
      "type": "string",
      "x-va-field": {
        "label": "Station Fax Number",
        "widget": "text"
      }
    },
    "stationEmailAddress2": {
      "type": "string",
      "format": "email",
      "x-va-field": {
        "label": "Station Email Address",
        "widget": "email"
      }
    },
    "payeeVendorTypeSelectOne": {
      "type": "string",
      "x-va-field": {
        "label": "PAYEE/VENDOR TYPE (Select one)",
        "widget": "text"
      }
    },
    "miscellaneousActionsSelectOne": {
      "type": "string",
      "x-va-field": {
        "label": "Miscellaneous Actions (Select One)",
        "widget": "text"
      }
    },
    "commercialVendorRegisteredInSamGov2": {
      "type": "string",
      "x-va-field": {
        "label": "Commercial Vendor Registered In Sam.Gov",
        "widget": "text"
      }
    },
    "uniqueEntityIdentifierUei": {
      "type": "string",
      "x-va-field": {
        "label": "Unique Entity Identifier (Uei)",
        "widget": "text"
      }
    },
    "eftIdentifer": {
      "type": "string",
      "x-va-field": {
        "label": "Eft Identifer",
        "widget": "text"
      }
    },
    "ssnTin3": {
      "type": "string",
      "pattern": "^\\d{3}-?\\d{2}-?\\d{4}$",
      "maxLength": 11,
      "x-va-field": {
        "label": "SSN/Tin",
        "widget": "ssn"
      }
    },
    "npi3": {
      "type": "string",
      "x-va-field": {
        "label": "NPI",
        "widget": "text"
      }
    },
    "smallBusiness2": {
      "type": "string",
      "x-va-field": {
        "label": "Small Business",
        "widget": "text"
      }
    },
    "payeeVendorName2": {
      "type": "string",
      "x-va-field": {
        "label": "Payee Vendor Name",
        "widget": "text"
      }
    },
    "doingBusinessAsDba2": {
      "type": "string",
      "x-va-field": {
        "label": "Doing Business As (Dba)",
        "widget": "text"
      }
    },
    "payeeVendorEmailAddress": {
      "type": "string",
      "format": "email",
      "x-va-field": {
        "label": "Payee Vendor Email Address",
        "widget": "email"
      }
    },
    "payeeVendorPhoneNumber2": {
      "type": "string",
      "pattern": "^\\d{10}$",
      "x-va-field": {
        "label": "Payee Vendor Phone Number",
        "widget": "phone"
      }
    },
    "currentAddressIncludeStreetCityStateAndZipCode": {
      "type": "string",
      "x-va-field": {
        "label": "Current Address Include Street City State and ZIP Code",
        "widget": "address"
      }
    },
    "previousAddressIncludeStreetCityStateAndZipCode": {
      "type": "string",
      "x-va-field": {
        "label": "Previous Address Include Street City State and ZIP Code",
        "widget": "address"
      }
    },
    "currentBankName2": {
      "type": "string",
      "x-va-field": {
        "label": "Current Bank Name",
        "widget": "text"
      }
    },
    "currentBankNineDigitRoutingNumber": {
      "type": "string",
      "x-va-field": {
        "label": "Current Bank Nine Digit Routing Number",
        "widget": "text"
      }
    },
    "currentBankAccountNumber2": {
      "type": "string",
      "x-va-field": {
        "label": "Current Bank Account Number",
        "widget": "text"
      }
    },
    "currentAccountType2": {
      "type": "string",
      "x-va-field": {
        "label": "Current Account Type",
        "widget": "text"
      }
    },
    "nameAndTitleOfAuthorizedRepresentative2": {
      "type": "string",
      "x-va-field": {
        "label": "Name and Title of Authorized Representative",
        "widget": "text"
      }
    },
    "signatureOfAuthorizedRepresentative2": {
      "type": "string",
      "x-va-field": {
        "label": "Signature of Authorized Representative",
        "widget": "signature"
      }
    },
    "forQuestionsRegardingThisForm": {
      "type": "string",
      "x-va-field": {
        "label": "For Questions Regarding This Form",
        "widget": "text"
      }
    },
    "vaFscCustomerEngagement": {
      "type": "string",
      "x-va-field": {
        "label": "VA Fsc Customer Engagement",
        "widget": "text"
      }
    },
    "phone2": {
      "type": "string",
      "pattern": "^\\d{10}$",
      "x-va-field": {
        "label": "Phone",
        "widget": "phone"
      }
    },
    "email2": {
      "type": "string",
      "format": "email",
      "x-va-field": {
        "label": "Email",
        "widget": "email"
      }
    },
    "forStationInquiries": {
      "type": "string",
      "x-va-field": {
        "label": "For Station Inquiries",
        "widget": "text"
      }
    },
    "stationCareCenter": {
      "type": "string",
      "x-va-field": {
        "label": "Station Care Center",
        "widget": "text"
      }
    },
    "paperworkReductionActStatement": {
      "type": "string",
      "x-va-field": {
        "label": "Paper Work Reduction Act Statement",
        "widget": "select"
      }
    }
  },
  "x-va-metadata": {
    "formUrl": "https://www.va.gov/vaforms/va/pdf/VA10091.pdf",
    "totalFields": 97,
    "composedFields": 95,
    "coveragePercent": 100,
    "xfaLabelCount": 27,
    "needsReviewCount": 0,
    "generatedAt": "2026-03-28T21:25:58.941Z",
    "pageCount": 3,
    "status": "digitized",
    "redigitizedAt": "2026-03-30T20:27:41.671Z",
    "extractionSources": [
      "acroform",
      "acroform+text-inference",
      "text-inference"
    ],
    "fieldNameFixedAt": "2026-03-31T01:08:01.968588+00:00"
  },
  "x-va-form": {
    "formNumber": "VA10091",
    "formTitle": "VA Form VA10091",
    "formSections": [
      {
        "title": "Financial Information",
        "rows": [
          {
            "columns": [
              {
                "fieldId": "bankName",
                "width": 12
              }
            ]
          },
          {
            "columns": [
              {
                "fieldId": "bankRoutingNumber",
                "width": 12
              }
            ]
          }
        ]
      },
      {
        "title": "Employment Information",
        "rows": [
          {
            "columns": [
              {
                "fieldId": "nameAndTitleOfAuthorizedRepresentative",
                "width": 12
              }
            ]
          },
          {
            "columns": [
              {
                "fieldId": "nameAndTitleOfAuthorizedRepresentative2",
                "width": 12
              }
            ]
          }
        ]
      },
      {
        "title": "Certification and Signature",
        "rows": [
          {
            "columns": [
              {
                "fieldId": "signatureOfAuthorizedRepresentative",
                "width": 12
              }
            ]
          },
          {
            "columns": [
              {
                "fieldId": "signatureOfAuthorizedRepresentative2",
                "width": 12
              }
            ]
          }
        ]
      },
      {
        "title": "Additional Information",
        "rows": [
          {
            "columns": [
              {
                "fieldId": "date",
                "width": 12
              }
            ]
          },
          {
            "columns": [
              {
                "fieldId": "stationNumber",
                "width": 12
              }
            ]
          },
          {
            "columns": [
              {
                "fieldId": "stationContact",
                "width": 12
              }
            ]
          },
          {
            "columns": [
              {
                "fieldId": "stationPhone",
                "width": 12
              }
            ]
          },
          {
            "columns": [
              {
                "fieldId": "stationFax",
                "width": 12
              }
            ]
          },
          {
            "columns": [
              {
                "fieldId": "stationEmail",
                "width": 12
              }
            ]
          },
          {
            "columns": [
              {
                "fieldId": "payee",
                "width": 12
              }
            ]
          },
          {
            "columns": [
              {
                "fieldId": "factsId",
                "width": 12
              }
            ]
          },
          {
            "columns": [
              {
                "fieldId": "miscellaneousActions",
                "width": 12
              }
            ]
          },
          {
            "columns": [
              {
                "fieldId": "martinsburgFallingwaters",
                "width": 12
              }
            ]
          },
          {
            "columns": [
              {
                "fieldId": "dunsNumber",
                "width": 12
              }
            ]
          },
          {
            "columns": [
              {
                "fieldId": "duns4",
                "width": 12
              }
            ]
          },
          {
            "columns": [
              {
                "fieldId": "ssnTin",
                "width": 12
              }
            ]
          },
          {
            "columns": [
              {
                "fieldId": "npi",
                "width": 12
              }
            ]
          },
          {
            "columns": [
              {
                "fieldId": "createNew",
                "width": 12
              }
            ]
          },
          {
            "columns": [
              {
                "fieldId": "payeeName",
                "width": 12
              }
            ]
          },
          {
            "columns": [
              {
                "fieldId": "dba",
                "width": 12
              }
            ]
          },
          {
            "columns": [
              {
                "fieldId": "email",
                "width": 12
              }
            ]
          },
          {
            "columns": [
              {
                "fieldId": "phone",
                "width": 12
              }
            ]
          },
          {
            "columns": [
              {
                "fieldId": "currentAddress",
                "width": 12
              }
            ]
          },
          {
            "columns": [
              {
                "fieldId": "previousAddress",
                "width": 12
              }
            ]
          },
          {
            "columns": [
              {
                "fieldId": "accountNumber",
                "width": 12
              }
            ]
          },
          {
            "columns": [
              {
                "fieldId": "accountType",
                "width": 12
              }
            ]
          },
          {
            "columns": [
              {
                "fieldId": "nameTitle",
                "width": 12
              }
            ]
          },
          {
            "columns": [
              {
                "fieldId": "fullName",
                "width": 12
              }
            ]
          },
          {
            "columns": [
              {
                "fieldId": "purposeOfForm",
                "width": 12
              }
            ]
          },
          {
            "columns": [
              {
                "fieldId": "establishOrUp",
                "width": 12
              }
            ]
          },
          {
            "columns": [
              {
                "fieldId": "requestType",
                "width": 12
              }
            ]
          },
          {
            "columns": [
              {
                "fieldId": "chooseUp",
                "width": 12
              }
            ]
          },
          {
            "columns": [
              {
                "fieldId": "stationNumber2",
                "width": 12
              }
            ]
          },
          {
            "columns": [
              {
                "fieldId": "stationContact2",
                "width": 12
              }
            ]
          },
          {
            "columns": [
              {
                "fieldId": "stationPhoneNumber",
                "width": 12
              }
            ]
          },
          {
            "columns": [
              {
                "fieldId": "stationFaxNumber",
                "width": 12
              }
            ]
          },
          {
            "columns": [
              {
                "fieldId": "stationEmailAddress",
                "width": 12
              }
            ]
          },
          {
            "columns": [
              {
                "fieldId": "payeeVendorTypeRequired",
                "width": 12
              }
            ]
          },
          {
            "columns": [
              {
                "fieldId": "miscellaneousActionsIfApplicable",
                "width": 12
              }
            ]
          },
          {
            "columns": [
              {
                "fieldId": "commercialVendorRegisteredInSamGov",
                "width": 12
              }
            ]
          },
          {
            "columns": [
              {
                "fieldId": "uniqueEntityIdentifyUei",
                "width": 12
              }
            ]
          },
          {
            "columns": [
              {
                "fieldId": "eftIndicator",
                "width": 12
              }
            ]
          },
          {
            "columns": [
              {
                "fieldId": "blankOrIncorrectInformationInThisFieldMayCauseA",
                "width": 12
              }
            ]
          },
          {
            "columns": [
              {
                "fieldId": "ssnTin2",
                "width": 12
              }
            ]
          },
          {
            "columns": [
              {
                "fieldId": "npi2",
                "width": 12
              }
            ]
          },
          {
            "columns": [
              {
                "fieldId": "smallBusiness",
                "width": 12
              }
            ]
          },
          {
            "columns": [
              {
                "fieldId": "payeeVendorName",
                "width": 12
              }
            ]
          },
          {
            "columns": [
              {
                "fieldId": "doingBusinessAsDba",
                "width": 12
              }
            ]
          },
          {
            "columns": [
              {
                "fieldId": "payeeVendorEmail",
                "width": 12
              }
            ]
          },
          {
            "columns": [
              {
                "fieldId": "emailAddressForThePersonListedInBoxes_24And_25",
                "width": 12
              }
            ]
          },
          {
            "columns": [
              {
                "fieldId": "payeeVendorPhoneNumber",
                "width": 12
              }
            ]
          },
          {
            "columns": [
              {
                "fieldId": "currentAddress2",
                "width": 12
              }
            ]
          },
          {
            "columns": [
              {
                "fieldId": "previousAddressRequiredForAddressChange",
                "width": 12
              }
            ]
          },
          {
            "columns": [
              {
                "fieldId": "requests",
                "width": 12
              }
            ]
          },
          {
            "columns": [
              {
                "fieldId": "currentBankName",
                "width": 12
              }
            ]
          },
          {
            "columns": [
              {
                "fieldId": "currentBank_9DigitRoutingNumber",
                "width": 12
              }
            ]
          },
          {
            "columns": [
              {
                "fieldId": "currentBankAccountNumber",
                "width": 12
              }
            ]
          },
          {
            "columns": [
              {
                "fieldId": "currentAccountType",
                "width": 12
              }
            ]
          },
          {
            "columns": [
              {
                "fieldId": "makesItACrimeTo",
                "width": 12
              }
            ]
          },
          {
            "columns": [
              {
                "fieldId": "representativeIsDefinedAs",
                "width": 12
              }
            ]
          },
          {
            "columns": [
              {
                "fieldId": "statementOnThisFormCanBePunishedByFineOr",
                "width": 12
              }
            ]
          },
          {
            "columns": [
              {
                "fieldId": "newVendorup",
                "width": 12
              }
            ]
          },
          {
            "columns": [
              {
                "fieldId": "stationNumber3",
                "width": 12
              }
            ]
          },
          {
            "columns": [
              {
                "fieldId": "stationContact3",
                "width": 12
              }
            ]
          },
          {
            "columns": [
              {
                "fieldId": "stationPhoneNumber2",
                "width": 12
              }
            ]
          },
          {
            "columns": [
              {
                "fieldId": "stationFaxNumber2",
                "width": 12
              }
            ]
          },
          {
            "columns": [
              {
                "fieldId": "stationEmailAddress2",
                "width": 12
              }
            ]
          },
          {
            "columns": [
              {
                "fieldId": "payeeVendorTypeSelectOne",
                "width": 12
              }
            ]
          },
          {
            "columns": [
              {
                "fieldId": "miscellaneousActionsSelectOne",
                "width": 12
              }
            ]
          },
          {
            "columns": [
              {
                "fieldId": "commercialVendorRegisteredInSamGov2",
                "width": 12
              }
            ]
          },
          {
            "columns": [
              {
                "fieldId": "uniqueEntityIdentifierUei",
                "width": 12
              }
            ]
          },
          {
            "columns": [
              {
                "fieldId": "eftIdentifer",
                "width": 12
              }
            ]
          },
          {
            "columns": [
              {
                "fieldId": "ssnTin3",
                "width": 12
              }
            ]
          },
          {
            "columns": [
              {
                "fieldId": "npi3",
                "width": 12
              }
            ]
          },
          {
            "columns": [
              {
                "fieldId": "smallBusiness2",
                "width": 12
              }
            ]
          },
          {
            "columns": [
              {
                "fieldId": "payeeVendorName2",
                "width": 12
              }
            ]
          },
          {
            "columns": [
              {
                "fieldId": "doingBusinessAsDba2",
                "width": 12
              }
            ]
          },
          {
            "columns": [
              {
                "fieldId": "payeeVendorEmailAddress",
                "width": 12
              }
            ]
          },
          {
            "columns": [
              {
                "fieldId": "payeeVendorPhoneNumber2",
                "width": 12
              }
            ]
          },
          {
            "columns": [
              {
                "fieldId": "currentAddressIncludeStreetCityStateAndZipCode",
                "width": 12
              }
            ]
          },
          {
            "columns": [
              {
                "fieldId": "previousAddressIncludeStreetCityStateAndZipCode",
                "width": 12
              }
            ]
          },
          {
            "columns": [
              {
                "fieldId": "currentBankName2",
                "width": 12
              }
            ]
          },
          {
            "columns": [
              {
                "fieldId": "currentBankNineDigitRoutingNumber",
                "width": 12
              }
            ]
          },
          {
            "columns": [
              {
                "fieldId": "currentBankAccountNumber2",
                "width": 12
              }
            ]
          },
          {
            "columns": [
              {
                "fieldId": "currentAccountType2",
                "width": 12
              }
            ]
          },
          {
            "columns": [
              {
                "fieldId": "forQuestionsRegardingThisForm",
                "width": 12
              }
            ]
          },
          {
            "columns": [
              {
                "fieldId": "vaFscCustomerEngagement",
                "width": 12
              }
            ]
          },
          {
            "columns": [
              {
                "fieldId": "phone2",
                "width": 12
              }
            ]
          },
          {
            "columns": [
              {
                "fieldId": "email2",
                "width": 12
              }
            ]
          },
          {
            "columns": [
              {
                "fieldId": "forStationInquiries",
                "width": 12
              }
            ]
          },
          {
            "columns": [
              {
                "fieldId": "stationCareCenter",
                "width": 12
              }
            ]
          },
          {
            "columns": [
              {
                "fieldId": "paperworkReductionActStatement",
                "width": 12
              }
            ]
          }
        ]
      }
    ]
  }
}